{
    "name": "root",
    "gauges": {
        "Landing.Policy.Entropy.mean": {
            "value": 1.7889962196350098,
            "min": 1.7670420408248901,
            "max": 1.7906692028045654,
            "count": 10
        },
        "Landing.Policy.Entropy.sum": {
            "value": 89698.484375,
            "min": 89132.71875,
            "max": 92605.375,
            "count": 10
        },
        "Landing.Step.mean": {
            "value": 499962.0,
            "min": 49956.0,
            "max": 499962.0,
            "count": 10
        },
        "Landing.Step.sum": {
            "value": 499962.0,
            "min": 49956.0,
            "max": 499962.0,
            "count": 10
        },
        "Landing.Policy.ExtrinsicValueEstimate.mean": {
            "value": -26.947891235351562,
            "min": -282.3247985839844,
            "max": 45.70125961303711,
            "count": 10
        },
        "Landing.Policy.ExtrinsicValueEstimate.sum": {
            "value": -24145.310546875,
            "min": -252398.359375,
            "max": 40948.328125,
            "count": 10
        },
        "Landing.Policy.GailValueEstimate.mean": {
            "value": 14.562469482421875,
            "min": 13.50249195098877,
            "max": 26.268659591674805,
            "count": 10
        },
        "Landing.Policy.GailValueEstimate.sum": {
            "value": 13047.97265625,
            "min": 12098.232421875,
            "max": 23326.5703125,
            "count": 10
        },
        "Landing.Losses.PolicyLoss.mean": {
            "value": 0.02405635703432684,
            "min": 0.022373966459029664,
            "max": 0.1418927627285787,
            "count": 10
        },
        "Landing.Losses.PolicyLoss.sum": {
            "value": 0.12028178517163421,
            "min": 0.09970164030479889,
            "max": 0.5675710509143148,
            "count": 10
        },
        "Landing.Losses.ValueLoss.mean": {
            "value": 57342.45582194011,
            "min": 4220.296625963847,
            "max": 142101.4624617513,
            "count": 10
        },
        "Landing.Losses.ValueLoss.sum": {
            "value": 286712.2791097005,
            "min": 16881.186503855388,
            "max": 710507.3123087565,
            "count": 10
        },
        "Landing.Policy.LearningRate.mean": {
            "value": 1.5306934897720002e-05,
            "min": 1.5306934897720002e-05,
            "max": 0.0002844303051899,
            "count": 10
        },
        "Landing.Policy.LearningRate.sum": {
            "value": 7.65346744886e-05,
            "min": 7.65346744886e-05,
            "max": 0.0012823284725571999,
            "count": 10
        },
        "Landing.Policy.Epsilon.mean": {
            "value": 0.10510228000000002,
            "min": 0.10510228000000002,
            "max": 0.19481010000000004,
            "count": 10
        },
        "Landing.Policy.Epsilon.sum": {
            "value": 0.5255114000000001,
            "min": 0.5255114000000001,
            "max": 0.9274428000000003,
            "count": 10
        },
        "Landing.Policy.Beta.mean": {
            "value": 0.00026460377200000003,
            "min": 0.00026460377200000003,
            "max": 0.004741023990000001,
            "count": 10
        },
        "Landing.Policy.Beta.sum": {
            "value": 0.0013230188600000003,
            "min": 0.0013230188600000003,
            "max": 0.02137939572,
            "count": 10
        },
        "Landing.Policy.GAILPolicyEstimate.mean": {
            "value": 0.376470083942016,
            "min": 0.3588529319564502,
            "max": 0.38377935508886973,
            "count": 10
        },
        "Landing.Policy.GAILPolicyEstimate.sum": {
            "value": 1.8823504197100798,
            "min": 1.4530864838180908,
            "max": 1.9188967754443487,
            "count": 10
        },
        "Landing.Policy.GAILExpertEstimate.mean": {
            "value": 0.6959147540728251,
            "min": 0.6734876132011414,
            "max": 0.698094418446223,
            "count": 10
        },
        "Landing.Policy.GAILExpertEstimate.sum": {
            "value": 3.4795737703641256,
            "min": 2.6974561184644696,
            "max": 3.4904720922311148,
            "count": 10
        },
        "Landing.Losses.GAILLoss.mean": {
            "value": 0.9637849414348603,
            "min": 0.8755922083059946,
            "max": 1.6692938273151716,
            "count": 10
        },
        "Landing.Losses.GAILLoss.sum": {
            "value": 4.818924707174301,
            "min": 3.8141898294289907,
            "max": 6.6771753092606865,
            "count": 10
        },
        "Landing.Policy.GAILGradMagLoss.mean": {
            "value": 0.41180998146533965,
            "min": 0.16664574936032298,
            "max": 1.9570335259040195,
            "count": 10
        },
        "Landing.Policy.GAILGradMagLoss.sum": {
            "value": 2.059049907326698,
            "min": 0.8332287468016149,
            "max": 7.828134103616078,
            "count": 10
        },
        "Landing.Environment.EpisodeLength.mean": {
            "value": 188.04119850187266,
            "min": 179.86194029850745,
            "max": 218.11737089201878,
            "count": 10
        },
        "Landing.Environment.EpisodeLength.sum": {
            "value": 50207.0,
            "min": 45862.0,
            "max": 52382.0,
            "count": 10
        },
        "Landing.Environment.CumulativeReward.mean": {
            "value": -141.19640170322376,
            "min": -1247.800242386465,
            "max": 335.21397013059806,
            "count": 10
        },
        "Landing.Environment.CumulativeReward.sum": {
            "value": -37699.43925476074,
            "min": -316941.2615661621,
            "max": 71400.57563781738,
            "count": 10
        },
        "Landing.Policy.ExtrinsicReward.mean": {
            "value": -141.19640170322376,
            "min": -1247.800242386465,
            "max": 335.21397013059806,
            "count": 10
        },
        "Landing.Policy.ExtrinsicReward.sum": {
            "value": -37699.43925476074,
            "min": -316941.2615661621,
            "max": 71400.57563781738,
            "count": 10
        },
        "Landing.Policy.GailReward.mean": {
            "value": 59.22339483130067,
            "min": 42.18148762154838,
            "max": 72.3216681044129,
            "count": 10
        },
        "Landing.Policy.GailReward.sum": {
            "value": 15812.64641995728,
            "min": 11304.638682574965,
            "max": 16303.649558476638,
            "count": 10
        },
        "Landing.IsTraining.mean": {
            "value": 1.0,
            "min": 1.0,
            "max": 1.0,
            "count": 10
        },
        "Landing.IsTraining.sum": {
            "value": 1.0,
            "min": 1.0,
            "max": 1.0,
            "count": 10
        }
    },
    "metadata": {
        "timer_format_version": "0.1.0",
        "start_time_seconds": "1692138408",
        "python_version": "3.9.7 (tags/v3.9.7:1016ef3, Aug 30 2021, 20:19:38) [MSC v.1929 64 bit (AMD64)]",
        "command_line_arguments": "D:\\Student Projects\\harryxu123\\My project\\venv\\Scripts\\mlagents-learn configs/landing.yaml --run-id=RefinedLandScaled8 --initialize-from=RefinedLandScaled7",
        "mlagents_version": "0.30.0",
        "mlagents_envs_version": "0.30.0",
        "communication_protocol_version": "1.5.0",
        "pytorch_version": "2.0.1+cpu",
        "numpy_version": "1.21.2",
        "end_time_seconds": "1692138656"
    },
    "total": 248.5117812,
    "count": 1,
    "self": 0.005416100000019242,
    "children": {
        "run_training.setup": {
            "total": 0.06677029999999995,
            "count": 1,
            "self": 0.06677029999999995
        },
        "TrainerController.start_learning": {
            "total": 248.43959479999998,
            "count": 1,
            "self": 0.16503679999917154,
            "children": {
                "TrainerController._reset_env": {
                    "total": 7.7300643,
                    "count": 1,
                    "self": 7.103278900000001,
                    "children": {
                        "demo_to_buffer": {
                            "total": 0.6267853999999993,
                            "count": 1,
                            "self": 7.699999999921658e-05,
                            "children": {
                                "load_demonstration": {
                                    "total": 0.011640399999999218,
                                    "count": 1,
                                    "self": 0.011490199999999007,
                                    "children": {
                                        "read_file": {
                                            "total": 0.00015020000000021128,
                                            "count": 1,
                                            "self": 0.00015020000000021128
                                        }
                                    }
                                },
                                "make_demo_buffer": {
                                    "total": 0.6150680000000008,
                                    "count": 1,
                                    "self": 0.13549679999989728,
                                    "children": {
                                        "steps_from_proto": {
                                            "total": 0.47957120000010356,
                                            "count": 7508,
                                            "self": 0.294283800000251,
                                            "children": {
                                                "_process_rank_one_or_two_observation": {
                                                    "total": 0.18528739999985255,
                                                    "count": 15016,
                                                    "self": 0.18528739999985255
                                                }
                                            }
                                        }
                                    }
                                }
                            }
                        }
                    }
                },
                "TrainerController.advance": {
                    "total": 240.5036619000008,
                    "count": 8152,
                    "self": 0.15276429999985908,
                    "children": {
                        "env_step": {
                            "total": 89.02118750000079,
                            "count": 8152,
                            "self": 79.59604059999909,
                            "children": {
                                "SubprocessEnvManager._take_step": {
                                    "total": 9.3405866000008,
                                    "count": 8152,
                                    "self": 0.47135119999957986,
                                    "children": {
                                        "TorchPolicy.evaluate": {
                                            "total": 8.86923540000122,
                                            "count": 6205,
                                            "self": 8.86923540000122
                                        }
                                    }
                                },
                                "workers": {
                                    "total": 0.08456030000090564,
                                    "count": 8152,
                                    "self": 0.0,
                                    "children": {
                                        "worker_root": {
                                            "total": 241.02736120000017,
                                            "count": 8152,
                                            "is_parallel": true,
                                            "self": 178.0055762000007,
                                            "children": {
                                                "steps_from_proto": {
                                                    "total": 0.0007292000000003185,
                                                    "count": 1,
                                                    "is_parallel": true,
                                                    "self": 0.00022050000000017889,
                                                    "children": {
                                                        "_process_rank_one_or_two_observation": {
                                                            "total": 0.0005087000000001396,
                                                            "count": 2,
                                                            "is_parallel": true,
                                                            "self": 0.0005087000000001396
                                                        }
                                                    }
                                                },
                                                "UnityEnvironment.step": {
                                                    "total": 63.021055799999466,
                                                    "count": 8152,
                                                    "is_parallel": true,
                                                    "self": 1.9506854999971637,
                                                    "children": {
                                                        "UnityEnvironment._generate_step_input": {
                                                            "total": 4.6847103000009955,
                                                            "count": 8152,
                                                            "is_parallel": true,
                                                            "self": 4.6847103000009955
                                                        },
                                                        "communicator.exchange": {
                                                            "total": 52.67950980000104,
                                                            "count": 8152,
                                                            "is_parallel": true,
                                                            "self": 52.67950980000104
                                                        },
                                                        "steps_from_proto": {
                                                            "total": 3.7061502000002635,
                                                            "count": 8152,
                                                            "is_parallel": true,
                                                            "self": 1.03719459999909,
                                                            "children": {
                                                                "_process_rank_one_or_two_observation": {
                                                                    "total": 2.6689556000011736,
                                                                    "count": 16304,
                                                                    "is_parallel": true,
                                                                    "self": 2.6689556000011736
                                                                }
                                                            }
                                                        }
                                                    }
                                                }
                                            }
                                        }
                                    }
                                }
                            }
                        },
                        "trainer_advance": {
                            "total": 151.32971010000014,
                            "count": 8152,
                            "self": 0.3648207000008199,
                            "children": {
                                "process_trajectory": {
                                    "total": 34.60190019999936,
                                    "count": 8152,
                                    "self": 34.53401539999936,
                                    "children": {
                                        "RLTrainer._checkpoint": {
                                            "total": 0.06788480000000163,
                                            "count": 1,
                                            "self": 0.06788480000000163
                                        }
                                    }
                                },
                                "_update_policy": {
                                    "total": 116.36298919999996,
                                    "count": 48,
                                    "self": 91.39321290000066,
                                    "children": {
                                        "TorchPPOOptimizer.update": {
                                            "total": 24.969776299999303,
                                            "count": 1440,
                                            "self": 24.969776299999303
                                        }
                                    }
                                }
                            }
                        }
                    }
                },
                "trainer_threads": {
                    "total": 9.000000034120603e-07,
                    "count": 1,
                    "self": 9.000000034120603e-07
                },
                "TrainerController._save_models": {
                    "total": 0.04083090000000311,
                    "count": 1,
                    "self": 0.0058848999999838725,
                    "children": {
                        "RLTrainer._checkpoint": {
                            "total": 0.03494600000001924,
                            "count": 1,
                            "self": 0.03494600000001924
                        }
                    }
                }
            }
        }
    }
}